[{
    "date": "2023-12-31",
    "clientASN": "36992",
    "clientCountry": "EG",
    "avg_download_speed": "744960.44",
    "avg_upload_speed": "1055781.5",
    "avg_latency": "255.58"
  }, {
    "date": "2023-12-31",
    "clientASN": "2561",
    "clientCountry": "EG",
    "avg_download_speed": "42675937.64",
    "avg_upload_speed": "32264270.44",
    "avg_latency": "55.25"
  }, {
    "date": "2023-12-31",
    "clientASN": "37564",
    "clientCountry": "ZA",
    "avg_download_speed": "24757777.54",
    "avg_upload_speed": "9476872.28",
    "avg_latency": "15.25"
  }, {
    "date": "2023-12-31",
    "clientASN": "29465",
    "clientCountry": "NG",
    "avg_download_speed": "6263510.83",
    "avg_upload_speed": "3967444.17",
    "avg_latency": "722.85"
  }, {
    "date": "2023-12-31",
    "clientASN": "8452",
    "clientCountry": "EG",
    "avg_download_speed": "15729719.71",
    "avg_upload_speed": "2023115.43",
    "avg_latency": "79.2"
  }, {
    "date": "2023-12-31",
    "clientASN": "29465",
    "clientCountry": "NG",
    "avg_download_speed": "30242234.37",
    "avg_upload_speed": "11318731.44",
    "avg_latency": "56.34"
  }, {
    "date": "2023-12-31",
    "clientASN": "8452",
    "clientCountry": "EG",
    "avg_download_speed": "17950930.87",
    "avg_upload_speed": "2294837.5",
    "avg_latency": "66.1"
  }, {
    "date": "2023-12-31",
    "clientASN": "37457",
    "clientCountry": "ZA",
    "avg_download_speed": "110598479.07",
    "avg_upload_speed": "49269945.18",
    "avg_latency": "79.9"
  }, {
    "date": "2023-12-31",
    "clientASN": "24863",
    "clientCountry": "EG",
    "avg_download_speed": "12291175.38",
    "avg_upload_speed": "1464118.86",
    "avg_latency": "83.88"
  }, {
    "date": "2023-12-31",
    "clientASN": "37447",
    "clientCountry": "CD",
    "avg_download_speed": "2570182.06",
    "avg_upload_speed": "1513485.79",
    "avg_latency": "114.82"
  }, {
    "date": "2023-12-31",
    "clientASN": "36925",
    "clientCountry": "MA",
    "avg_download_speed": "18076675.79",
    "avg_upload_speed": "13863322.28",
    "avg_latency": "24.04"
  }, {
    "date": "2023-12-31",
    "clientASN": "36874",
    "clientCountry": "ZA",
    "avg_download_speed": "75264543.89",
    "avg_upload_speed": "51772660.05",
    "avg_latency": "14.77"
  }, {
    "date": "2023-12-31",
    "clientASN": "8452",
    "clientCountry": "EG",
    "avg_download_speed": "12115662.54",
    "avg_upload_speed": "1452815.14",
    "avg_latency": "163.4"
  }, {
    "date": "2023-12-31",
    "clientASN": "36977",
    "clientCountry": "UG",
    "avg_download_speed": "35957324.64",
    "avg_upload_speed": "18246446.61",
    "avg_latency": "78.9"
  }, {
    "date": "2023-12-31",
    "clientASN": "36994",
    "clientCountry": "ZA",
    "avg_download_speed": "3860024.08",
    "avg_upload_speed": "1870847.21",
    "avg_latency": "458.62"
  }, {
    "date": "2023-12-31",
    "clientASN": "24835",
    "clientCountry": "EG",
    "avg_download_speed": "18658106.38",
    "avg_upload_speed": "2533255.07",
    "avg_latency": "56.43"
  }, {
    "date": "2023-12-31",
    "clientASN": "36903",
    "clientCountry": "MA",
    "avg_download_speed": "40026761.92",
    "avg_upload_speed": "32058007.33",
    "avg_latency": "21.6"
  }, {
    "date": "2023-12-31",
    "clientASN": "36992",
    "clientCountry": "EG",
    "avg_download_speed": "29787616.96",
    "avg_upload_speed": "15700227.78",
    "avg_latency": "42.01"
  }, {
    "date": "2023-12-31",
    "clientASN": "328471",
    "clientCountry": "ZA",
    "avg_download_speed": "3360703.67",
    "avg_upload_speed": "4408020.29",
    "avg_latency": "26.83"
  }, {
    "date": "2023-12-31",
    "clientASN": "24863",
    "clientCountry": "EG",
    "avg_download_speed": "17868253.75",
    "avg_upload_speed": "2345393.0",
    "avg_latency": "62.13"
  }, {
    "date": "2023-12-31",
    "clientASN": "24863",
    "clientCountry": "EG",
    "avg_download_speed": "17592672.63",
    "avg_upload_speed": "2385556.86",
    "avg_latency": "63.34"
  }, {
    "date": "2023-12-31",
    "clientASN": "24863",
    "clientCountry": "EG",
    "avg_download_speed": "12290732.38",
    "avg_upload_speed": "2207276.71",
    "avg_latency": "94.86"
  }, {
    "date": "2023-12-31",
    "clientASN": "13335",
    "clientCountry": "TZ",
    "avg_download_speed": "19358867.0",
    "avg_upload_speed": "21740136.06",
    "avg_latency": "63.4"
  }, {
    "date": "2023-12-31",
    "clientASN": "29465",
    "clientCountry": "NG",
    "avg_download_speed": "3667480.83",
    "avg_upload_speed": "1106553.5",
    "avg_latency": "213.71"
  }, {
    "date": "2023-12-31",
    "clientASN": "328257",
    "clientCountry": "ZA",
    "avg_download_speed": "8512599.83",
    "avg_upload_speed": "3764330.79",
    "avg_latency": "89.21"
  }, {
    "date": "2023-12-31",
    "clientASN": "36994",
    "clientCountry": "ZA",
    "avg_download_speed": "34777665.17",
    "avg_upload_speed": "39997889.41",
    "avg_latency": "29.64"
  }, {
    "date": "2023-12-31",
    "clientASN": "37542",
    "clientCountry": "ZA",
    "avg_download_speed": "154986801.42",
    "avg_upload_speed": "138239800.76",
    "avg_latency": "13.97"
  }, {
    "date": "2023-12-31",
    "clientASN": "24835",
    "clientCountry": "EG",
    "avg_download_speed": "6087415.62",
    "avg_upload_speed": "692435.14",
    "avg_latency": "151.97"
  }, {
    "date": "2023-12-31",
    "clientASN": "8452",
    "clientCountry": "EG",
    "avg_download_speed": "6391990.46",
    "avg_upload_speed": "905160.64",
    "avg_latency": "122.38"
  }, {
    "date": "2023-12-31",
    "clientASN": "37457",
    "clientCountry": "ZA",
    "avg_download_speed": "115203184.64",
    "avg_upload_speed": "47181201.28",
    "avg_latency": "11.2"
  }, {
    "date": "2023-12-31",
    "clientASN": "36874",
    "clientCountry": "ZA",
    "avg_download_speed": null,
    "avg_upload_speed": null,
    "avg_latency": null
  }, {
    "date": "2023-12-31",
    "clientASN": "36977",
    "clientCountry": "UG",
    "avg_download_speed": "27563740.92",
    "avg_upload_speed": "18028378.83",
    "avg_latency": "81.1"
  }, {
    "date": "2023-12-31",
    "clientASN": "20011",
    "clientCountry": "ZA",
    "avg_download_speed": "3777357.67",
    "avg_upload_speed": "8467950.5",
    "avg_latency": "46.78"
  }, {
    "date": "2023-12-31",
    "clientASN": "37564",
    "clientCountry": "ZA",
    "avg_download_speed": "30866519.29",
    "avg_upload_speed": "10023373.06",
    "avg_latency": "12.53"
  }, {
    "date": "2023-12-31",
    "clientASN": "2561",
    "clientCountry": "EG",
    "avg_download_speed": "49322253.46",
    "avg_upload_speed": "33056660.5",
    "avg_latency": "46.25"
  }, {
    "date": "2023-12-31",
    "clientASN": "327752",
    "clientCountry": "LY",
    "avg_download_speed": "239586766.74",
    "avg_upload_speed": "54744768.0",
    "avg_latency": "21.78"
  }, {
    "date": "2023-12-31",
    "clientASN": "13335",
    "clientCountry": "ZA",
    "avg_download_speed": "158474078.25",
    "avg_upload_speed": "87121915.77",
    "avg_latency": "13.88"
  }, {
    "date": "2023-12-31",
    "clientASN": "37457",
    "clientCountry": "ZA",
    "avg_download_speed": "5976487.61",
    "avg_upload_speed": "15599522.94",
    "avg_latency": "16.33"
  }, {
    "date": "2023-12-31",
    "clientASN": "37020",
    "clientCountry": "CD",
    "avg_download_speed": "4758954.67",
    "avg_upload_speed": "4548749.14",
    "avg_latency": "64.79"
  }, {
    "date": "2023-12-31",
    "clientASN": "33771",
    "clientCountry": "KE",
    "avg_download_speed": "338697.5",
    "avg_upload_speed": "1432555.86",
    "avg_latency": "139.59"
  }, {
    "date": "2023-12-31",
    "clientASN": "24835",
    "clientCountry": "EG",
    "avg_download_speed": "19331518.0",
    "avg_upload_speed": "2155196.43",
    "avg_latency": "52.84"
  }, {
    "date": "2023-12-31",
    "clientASN": "8849",
    "clientCountry": "NG",
    "avg_download_speed": "7142797.38",
    "avg_upload_speed": "5285282.11",
    "avg_latency": "392.1"
  }, {
    "date": "2023-12-31",
    "clientASN": "24863",
    "clientCountry": "EG",
    "avg_download_speed": "14169719.33",
    "avg_upload_speed": "2285584.43",
    "avg_latency": "99.05"
  }, {
    "date": "2023-12-31",
    "clientASN": "8452",
    "clientCountry": "EG",
    "avg_download_speed": "19393205.25",
    "avg_upload_speed": "1734881.29",
    "avg_latency": "87.17"
  }, {
    "date": "2023-12-31",
    "clientASN": "15399",
    "clientCountry": "TZ",
    "avg_download_speed": "50245164.07",
    "avg_upload_speed": "42158425.36",
    "avg_latency": "15.4"
  }, {
    "date": "2023-12-31",
    "clientASN": "37282",
    "clientCountry": "NG",
    "avg_download_speed": "7763847.21",
    "avg_upload_speed": "10515465.83",
    "avg_latency": "61.72"
  }, {
    "date": "2023-12-31",
    "clientASN": "37577",
    "clientCountry": "BF",
    "avg_download_speed": "31835645.0",
    "avg_upload_speed": "14268014.5",
    "avg_latency": "24.2"
  }, {
    "date": "2023-12-31",
    "clientASN": "24863",
    "clientCountry": "EG",
    "avg_download_speed": "17468708.29",
    "avg_upload_speed": "2241608.86",
    "avg_latency": "72.81"
  }, {
    "date": "2023-12-31",
    "clientASN": "24863",
    "clientCountry": "EG",
    "avg_download_speed": "9129316.17",
    "avg_upload_speed": "2184911.93",
    "avg_latency": "102.77"
  }, {
    "date": "2023-12-31",
    "clientASN": "8452",
    "clientCountry": "EG",
    "avg_download_speed": "9622590.75",
    "avg_upload_speed": "678027.63",
    "avg_latency": "75.54"
  }, {
    "date": "2023-12-31",
    "clientASN": "24863",
    "clientCountry": "EG",
    "avg_download_speed": "10456874.92",
    "avg_upload_speed": "2296717.36",
    "avg_latency": "78.14"
  }, {
    "date": "2023-12-31",
    "clientASN": "37105",
    "clientCountry": "ZA",
    "avg_download_speed": "23410963.71",
    "avg_upload_speed": "18179643.11",
    "avg_latency": "41.75"
  }, {
    "date": "2023-12-31",
    "clientASN": "8452",
    "clientCountry": "EG",
    "avg_download_speed": "8499466.63",
    "avg_upload_speed": "1275249.71",
    "avg_latency": "153.41"
  }, {
    "date": "2023-12-31",
    "clientASN": "37204",
    "clientCountry": "ZW",
    "avg_download_speed": "21703316.08",
    "avg_upload_speed": "16861756.67",
    "avg_latency": "14.85"
  }, {
    "date": "2023-12-31",
    "clientASN": "328257",
    "clientCountry": "ZA",
    "avg_download_speed": "9169240.17",
    "avg_upload_speed": "3821822.64",
    "avg_latency": "102.28"
  }, {
    "date": "2023-12-31",
    "clientASN": "328442",
    "clientCountry": "CD",
    "avg_download_speed": "112254880.25",
    "avg_upload_speed": "61900741.27",
    "avg_latency": "4.45"
  }, {
    "date": "2023-12-31",
    "clientASN": "37457",
    "clientCountry": "ZA",
    "avg_download_speed": "89469885.86",
    "avg_upload_speed": "57885921.77",
    "avg_latency": "10.2"
  }, {
    "date": "2023-12-31",
    "clientASN": "37542",
    "clientCountry": "ZA",
    "avg_download_speed": "155901565.52",
    "avg_upload_speed": "139532845.04",
    "avg_latency": "12.89"
  }, {
    "date": "2023-12-31",
    "clientASN": "24863",
    "clientCountry": "EG",
    "avg_download_speed": "202916098.61",
    "avg_upload_speed": "38058383.59",
    "avg_latency": "48.9"
  }, {
    "date": "2023-12-31",
    "clientASN": "8452",
    "clientCountry": "EG",
    "avg_download_speed": "3478334.22",
    "avg_upload_speed": "404091.88",
    "avg_latency": "83.68"
  }, {
    "date": "2023-12-31",
    "clientASN": "8452",
    "clientCountry": "EG",
    "avg_download_speed": "14137050.83",
    "avg_upload_speed": "2321870.93",
    "avg_latency": "67.03"
  }, {
    "date": "2023-12-31",
    "clientASN": "36924",
    "clientCountry": "CG",
    "avg_download_speed": "17564745.33",
    "avg_upload_speed": "10965334.33",
    "avg_latency": "94.06"
  }, {
    "date": "2023-12-31",
    "clientASN": "29465",
    "clientCountry": "NG",
    "avg_download_speed": "7256759.04",
    "avg_upload_speed": "1088086.86",
    "avg_latency": "559.54"
  }, {
    "date": "2023-12-31",
    "clientASN": "8452",
    "clientCountry": "EG",
    "avg_download_speed": "11809882.38",
    "avg_upload_speed": "2276700.29",
    "avg_latency": "75.48"
  }, {
    "date": "2023-12-31",
    "clientASN": "8452",
    "clientCountry": "EG",
    "avg_download_speed": "32693723.21",
    "avg_upload_speed": "14776087.56",
    "avg_latency": "38.46"
  }, {
    "date": "2023-12-31",
    "clientASN": "329029",
    "clientCountry": "KE",
    "avg_download_speed": "10816503.58",
    "avg_upload_speed": "14460953.28",
    "avg_latency": "11.2"
  }, {
    "date": "2023-12-31",
    "clientASN": "29465",
    "clientCountry": "NG",
    "avg_download_speed": "7548536.21",
    "avg_upload_speed": "1169605.29",
    "avg_latency": "607.33"
  }, {
    "date": "2023-12-31",
    "clientASN": "8452",
    "clientCountry": "EG",
    "avg_download_speed": "10335688.5",
    "avg_upload_speed": "1483362.0",
    "avg_latency": "125.92"
  }, {
    "date": "2023-12-31",
    "clientASN": "328471",
    "clientCountry": "ZA",
    "avg_download_speed": "3242330.39",
    "avg_upload_speed": "3971401.43",
    "avg_latency": "22.52"
  }, {
    "date": "2023-12-31",
    "clientASN": "0",
    "clientCountry": "ZW",
    "avg_download_speed": "21609748.08",
    "avg_upload_speed": "24210221.67",
    "avg_latency": "30.1"
  }, {
    "date": "2023-12-31",
    "clientASN": "2561",
    "clientCountry": "EG",
    "avg_download_speed": "43113149.57",
    "avg_upload_speed": "29300190.44",
    "avg_latency": "54.9"
  }, {
    "date": "2023-12-31",
    "clientASN": "2561",
    "clientCountry": "EG",
    "avg_download_speed": "48119687.61",
    "avg_upload_speed": "41258144.68",
    "avg_latency": "46.4"
  }, {
    "date": "2023-12-31",
    "clientASN": "328471",
    "clientCountry": "ZA",
    "avg_download_speed": "3148339.39",
    "avg_upload_speed": "3474598.93",
    "avg_latency": "47.14"
  }, {
    "date": "2023-12-31",
    "clientASN": "37447",
    "clientCountry": "CD",
    "avg_download_speed": "5488938.46",
    "avg_upload_speed": "4875961.86",
    "avg_latency": "67.41"
  }, {
    "date": "2023-12-31",
    "clientASN": "8452",
    "clientCountry": "EG",
    "avg_download_speed": "2279333.67",
    "avg_upload_speed": "1989119.21",
    "avg_latency": "129.65"
  }, {
    "date": "2023-12-31",
    "clientASN": "37105",
    "clientCountry": "ZA",
    "avg_download_speed": "10667183.67",
    "avg_upload_speed": "3562318.43",
    "avg_latency": "100.13"
  }, {
    "date": "2023-12-31",
    "clientASN": "36994",
    "clientCountry": "ZA",
    "avg_download_speed": "13129716.79",
    "avg_upload_speed": "20048809.56",
    "avg_latency": "468.63"
  }, {
    "date": "2023-12-31",
    "clientASN": "328257",
    "clientCountry": "ZA",
    "avg_download_speed": "16247875.12",
    "avg_upload_speed": "3131561.21",
    "avg_latency": "82.77"
  }, {
    "date": "2023-12-31",
    "clientASN": "8452",
    "clientCountry": "EG",
    "avg_download_speed": "29480587.88",
    "avg_upload_speed": "14141758.56",
    "avg_latency": "39.65"
  }, {
    "date": "2023-12-31",
    "clientASN": "328719",
    "clientCountry": "ZA",
    "avg_download_speed": "3582303.67",
    "avg_upload_speed": "3542724.93",
    "avg_latency": "39.65"
  }, {
    "date": "2023-12-31",
    "clientASN": "11845",
    "clientCountry": "ZA",
    "avg_download_speed": "75872194.0",
    "avg_upload_speed": "21011697.44",
    "avg_latency": "19.86"
  }, {
    "date": "2023-12-31",
    "clientASN": "37645",
    "clientCountry": "AO",
    "avg_download_speed": "15660306.75",
    "avg_upload_speed": "6753078.56",
    "avg_latency": "12.36"
  }, {
    "date": "2023-12-31",
    "clientASN": "37457",
    "clientCountry": "ZA",
    "avg_download_speed": "1660553.44",
    "avg_upload_speed": "1588561.29",
    "avg_latency": "78.01"
  }, {
    "date": "2023-12-31",
    "clientASN": "37105",
    "clientCountry": "ZA",
    "avg_download_speed": "22515620.58",
    "avg_upload_speed": "7270740.11",
    "avg_latency": "25.25"
  }, {
    "date": "2023-12-31",
    "clientASN": "37457",
    "clientCountry": "ZA",
    "avg_download_speed": "74833548.43",
    "avg_upload_speed": "43967372.22",
    "avg_latency": "12.0"
  }, {
    "date": "2023-12-31",
    "clientASN": "16637",
    "clientCountry": "ZA",
    "avg_download_speed": "16037278.92",
    "avg_upload_speed": "3802231.5",
    "avg_latency": "41.63"
  }, {
    "date": "2023-12-31",
    "clientASN": "37457",
    "clientCountry": "ZA",
    "avg_download_speed": "56265790.88",
    "avg_upload_speed": "48607613.23",
    "avg_latency": "13.35"
  }, {
    "date": "2023-12-31",
    "clientASN": "20011",
    "clientCountry": "ZA",
    "avg_download_speed": "20836564.96",
    "avg_upload_speed": "12700899.06",
    "avg_latency": "64.2"
  }, {
    "date": "2023-12-31",
    "clientASN": "36992",
    "clientCountry": "EG",
    "avg_download_speed": "41806412.88",
    "avg_upload_speed": "5230583.36",
    "avg_latency": "14.85"
  }, {
    "date": "2023-12-31",
    "clientASN": "327752",
    "clientCountry": "LY",
    "avg_download_speed": "7981871.75",
    "avg_upload_speed": "4627353.79",
    "avg_latency": "60.09"
  }, {
    "date": "2023-12-31",
    "clientASN": "36873",
    "clientCountry": "NG",
    "avg_download_speed": "11067375.54",
    "avg_upload_speed": "6032347.33",
    "avg_latency": "72.67"
  }, {
    "date": "2023-12-31",
    "clientASN": "24835",
    "clientCountry": "EG",
    "avg_download_speed": "16375187.54",
    "avg_upload_speed": "1742713.07",
    "avg_latency": "63.8"
  }, {
    "date": "2023-12-31",
    "clientASN": "36992",
    "clientCountry": "EG",
    "avg_download_speed": "38976729.58",
    "avg_upload_speed": "5659549.14",
    "avg_latency": "15.3"
  }, {
    "date": "2023-12-31",
    "clientASN": "36992",
    "clientCountry": "EG",
    "avg_download_speed": "42181700.63",
    "avg_upload_speed": "5633656.71",
    "avg_latency": "12.6"
  }, {
    "date": "2023-12-31",
    "clientASN": "36873",
    "clientCountry": "NG",
    "avg_download_speed": "7108480.21",
    "avg_upload_speed": "4989012.07",
    "avg_latency": "58.39"
  }, {
    "date": "2023-12-31",
    "clientASN": "37457",
    "clientCountry": "ZA",
    "avg_download_speed": "3422885.61",
    "avg_upload_speed": "11762154.72",
    "avg_latency": "14.85"
  }, {
    "date": "2023-12-31",
    "clientASN": "8452",
    "clientCountry": "EG",
    "avg_download_speed": "26695652.33",
    "avg_upload_speed": "12460697.28",
    "avg_latency": "39.82"
  }, {
    "date": "2023-12-31",
    "clientASN": "30986",
    "clientCountry": "GH",
    "avg_download_speed": "21468857.13",
    "avg_upload_speed": "5023789.67",
    "avg_latency": "105.59"
  }, {
    "date": "2023-12-31",
    "clientASN": "36994",
    "clientCountry": "ZA",
    "avg_download_speed": "43448152.33",
    "avg_upload_speed": "35229945.22",
    "avg_latency": "137.57"
  }, {
    "date": "2023-12-31",
    "clientASN": "24863",
    "clientCountry": "EG",
    "avg_download_speed": "12346936.96",
    "avg_upload_speed": "2277553.86",
    "avg_latency": "95.95"
  }]